NebulaBayes/NB0_Main.py
NebulaBayes/NB1_Process_grids.py
NebulaBayes/NB2_Prior.py
NebulaBayes/NB3_Bayes.py
NebulaBayes/NB4_Plotting.py
NebulaBayes/__init__.py
NebulaBayes/_compat.py
NebulaBayes/_version.py
NebulaBayes/dereddening.py
NebulaBayes/docs/0_Getting_started.txt
NebulaBayes/docs/1_Example-basic.py
NebulaBayes/docs/2_Example-advanced.py
NebulaBayes/docs/changelog.txt
NebulaBayes/grids/Linelist.csv
NebulaBayes/grids/NB_HII_grid.fits.gz
NebulaBayes/grids/NB_NLR_grid.fits.gz
NebulaBayes/tests/run_tests.sh
NebulaBayes/tests/test_NB.py
NebulaBayes/tests/test_outputs/test_outputs_go_here
NebulaBayes-0.9.9.dist-info/LICENSE.txt
NebulaBayes-0.9.9.dist-info/METADATA
NebulaBayes-0.9.9.dist-info/WHEEL
NebulaBayes-0.9.9.dist-info/top_level.txt
NebulaBayes-0.9.9.dist-info/RECORD
