Metadata-Version: 2.1
Name: NebulaBayes
Version: 0.9.9
Summary: Compare observed emission line fluxes to predictions
Home-page: UNKNOWN
Author: Adam D. Thomas
Author-email: adam.thomas@anu.edu.au
License: MIT
Keywords: astronomy,Bayesian statistics
Platform: UNKNOWN
Classifier: Development Status :: 5 - Production/Stable
Classifier: Intended Audience :: Science/Research
Classifier: Natural Language :: English
Classifier: License :: OSI Approved :: MIT License
Classifier: Operating System :: OS Independent
Classifier: Programming Language :: Python
Classifier: Programming Language :: Python :: 2
Classifier: Programming Language :: Python :: 3
Classifier: Topic :: Scientific/Engineering :: Astronomy
Requires-Dist: astropy (>=1.1.0)
Requires-Dist: matplotlib
Requires-Dist: numpy
Requires-Dist: pandas
Requires-Dist: scipy
